{
    "chara":[
        {"id":0, "name":[
            "圣诞老人 :",
            "Santa :"
        ],"color":[180,82,82],
    "sound":"talk"},
        {"id":1, "name":[
            "小精灵 :",
            "Elfin :"
        ],"color":[138,176,96],
        "sound":"spriteTalk"},
        {"id":2, "name":[
            "作者 :",
            "Developer :"
        ],"color":[75,128,202],"sound":"authorTalk"}
    ],
    "data":[
        {
            "talker":1,
            "content":[
                "观众朋友们",
                "Ladies and gentlemen"
            ]
        },
        {
            "talker":1,
            "content":[
                "欢迎来到圣诞老人的直播间",
                " Welcome to Santa's live stream"
            ]
        },
        {
            
            "talker":1,
            "content":[
                "这里是圣诞直播夜现场",
                "This is the live broadcast of Santa's Night"
            ]
        },
        {
            
            "talker":1,
            "content":[
                "今夜...",
                "Tonight..."
            ]
        },
        {
            
            "talker":1,
            "content":[
                "每个好孩子都会收到礼物！",
                "Every good child will receive a gift!"
            ]
        },
        {
            
            "talker":0,
            "content":[
                "HOHOHO！祝你们圣诞节快乐！",
                "HOHOHO! Merry Christmas to you all!"
            ]
        },
        {
            
            "talker":1,
            "content":[
                "圣诞节快乐！",
                "Merry Christmas!"
            ]
        },
        {
            
            "talker":0,
            "content":[
                "迎接即将到来的2025年吧！",
                "Let's welcome the upcoming year of 2025!"
            ]
        },
        {
            
            "talker":2,
            "content":[
                "圣诞节快乐！",
                "Merry Christmas!"
            ]
        }
    ]
}